pysmad/__init__.py
pysmad/messages.py
pysmad/time.py
pysmad/bodies/__init__.py
pysmad/bodies/artificial.py
pysmad/bodies/celestial.py
pysmad/bodies/terrestrial.py
pysmad/coordinates/__init__.py
pysmad/coordinates/elements.py
pysmad/coordinates/positions.py
pysmad/coordinates/states.py
pysmad/estimation/__init__.py
pysmad/estimation/filtering.py
pysmad/estimation/iod.py
pysmad/estimation/obs.py
pysmad/hardware/__init__.py
pysmad/hardware/constraints.py
pysmad/hardware/payloads.py
pysmad/math/__init__.py
pysmad/math/constants.py
pysmad/math/functions.py
pysmad/math/linalg.py
pysmad/planning/__init__.py
pysmad/planning/maneuvers.py
pysmad/propagators/__init__.py
pysmad/propagators/inertial.py
pysmad/propagators/relative.py
pysmad-0.1.0.dist-info/METADATA
pysmad-0.1.0.dist-info/WHEEL
pysmad-0.1.0.dist-info/RECORD
