Metadata-Version: 2.3
Name: pysmad
Version: 0.1.0
Summary: Python package for space mission analysis and design
Project-URL: Documentation, https://www.pysmad.org/
Project-URL: Repository, https://github.com/brandon-sexton/pysmad
Author-email: Brandon Sexton <brandon.sexton.1@outlook.com>
License-Expression: GPL-3.0
Requires-Python: >=3.10
Provides-Extra: build
Requires-Dist: build; extra == 'build'
Provides-Extra: deploy
Requires-Dist: twine; extra == 'deploy'
Provides-Extra: dev
Requires-Dist: black; extra == 'dev'
Requires-Dist: flake8; extra == 'dev'
Requires-Dist: flake8-pytest-style; extra == 'dev'
Requires-Dist: isort; extra == 'dev'
Requires-Dist: mockito; extra == 'dev'
Requires-Dist: mypy; extra == 'dev'
Requires-Dist: pre-commit; extra == 'dev'
Requires-Dist: pytest; extra == 'dev'
Requires-Dist: pytest-cov; extra == 'dev'
Provides-Extra: docs
Requires-Dist: sphinx; extra == 'docs'
Requires-Dist: sphinx-rtd-theme; extra == 'docs'
Provides-Extra: test
Requires-Dist: mockito; extra == 'test'
Requires-Dist: pytest; extra == 'test'
Requires-Dist: pytest-cov; extra == 'test'
